MANIFEST.in
README.rst
setup.py
./annopyte/__init__.py
./annopyte/function_copy.py
./annopyte/annotations/__init__.py
./annopyte/annotations/signature.py
./annopyte/test/__init__.py
./annopyte/test/test_signature_annotations.py
annopyte.egg-info/PKG-INFO
annopyte.egg-info/SOURCES.txt
annopyte.egg-info/dependency_links.txt
annopyte.egg-info/not-zip-safe
annopyte.egg-info/top_level.txt