Metadata-Version: 1.0
Name: annopyte
Version: 0.2.1
Summary: python based tool for annotation and annotation processing.
Home-page: http://annopyte.franzoni.eu
Author: Alan Franzoni
Author-email: username@franzoni.eu
License: APL 2.0
Keywords: annotations metadata
Platform: UNKNOWN
